espie_character_gen-0.1.0.dist-info/METADATA
espie_character_gen-0.1.0.dist-info/WHEEL
espie_character_gen-0.1.0.dist-info/entry_points.txt
espie_character_gen-0.1.0.dist-info/licenses/LICENSE
espie_character_gen/__init__.py
espie_character_gen/__main__.py
espie_character_gen/app.py
espie_character_gen/rest_app/__init__.py
espie_character_gen/rest_app/authentication.py
espie_character_gen/rest_app/model.py
espie_character_gen/server.py
espie_character_gen/templates/base.html
espie_character_gen/templates/index.html
espie_character_gen/templates/login.html
espie_character_gen-0.1.0.dist-info/RECORD
