Metadata-Version: 2.1
Name: espie_character_gen
Version: 0.1.0
Summary: A Character creation app that will allow you to mess around with the different things and work with the within the rules of the Esper Genesis Role Playing Game based on the Core Manual
Keywords: game,api,dice
Author-Email: Andres Carrera <andreshcar@live.com>
Classifier: Intended Audience :: Information Technology
Classifier: Intended Audience :: Developers
Classifier: Operating System :: OS Independent
Classifier: Topic :: Software Development :: Libraries :: Python Modules
Classifier: Topic :: Software Development :: Libraries
Classifier: Topic :: Software Development
Classifier: License :: OSI Approved :: MIT License
Classifier: Programming Language :: Python :: 3 :: Only
Classifier: Programming Language :: Python :: 3.10
Classifier: Programming Language :: Python :: 3.11
Classifier: Programming Language :: Python :: 3.12
Project-URL: Homepage, https://github.com/carrera-dev-consulting/esper-genesis-character-creator
Project-URL: Documentation, https://consulting.gxldcptrick.dev/esper-genesis-character-creator/docs
Project-URL: Repository, https://github.com/carrera-dev-consulting/esper-genesis-character-creator
Project-URL: Issues, https://github.com/carrera-dev-consulting/esper-genesis-character-creator/issues
Project-URL: Changelog, https://github.com/carrera-dev-consulting/esper-genesis-character-creator/releases
Requires-Python: >=3.10
Requires-Dist: click>=8.1.7
Requires-Dist: fastapi>=0.115.0
Requires-Dist: uvicorn>=0.31.1
Requires-Dist: ariadne>=0.23.0
Requires-Dist: pydantic-settings>=2.6.1
Requires-Dist: pyjwt>=2.10.1
Requires-Dist: fastapi-sessions>=0.3.2
Requires-Dist: python-multipart>=0.0.20
